dbcontroller/__init__.py
dbcontroller/core/__init__.py
dbcontroller/core/annotations.py
dbcontroller/core/app.py
dbcontroller/core/base.py
dbcontroller/core/custom_class.py
dbcontroller/core/scalars.py
dbcontroller/core/spoc.py
dbcontroller/core/table.py
dbcontroller/forms.py
dbcontroller/manager/__init__.py
dbcontroller/manager/admin.py
dbcontroller/manager/mongo.py
dbcontroller/manager/sql.py
dbcontroller/manager/utils/__init__.py
dbcontroller/manager/utils/ids.py
dbcontroller/manager/utils/mongo_where.py
dbcontroller/manager/utils/object_id.py
dbcontroller/manager/utils/pagination.py
dbcontroller/manager/utils/response.py
dbcontroller/manager/utils/row_handler.py
dbcontroller/manager/utils/sql_where.py
dbcontroller/models/__init__.py
dbcontroller/models/mongo.py
dbcontroller/models/sql.py
dbcontroller/tools/__init__.py
dbcontroller-0.1.57.dist-info/WHEEL
dbcontroller-0.1.57.dist-info/METADATA
dbcontroller-0.1.57.dist-info/licenses/LICENSE.txt
dbcontroller-0.1.57.dist-info/RECORD
