Metadata-Version: 2.1
Name: dbcontroller
Version: 0.1.57
Summary: Python - Database Controller (SQLAlchemy & Motor)
Keywords: database,sql,mongo
Author-email: hlop3z <23062270+hlop3z@users.noreply.github.com>
Requires-Python: >=3.10
Classifier: Intended Audience :: Developers
Classifier: License :: OSI Approved :: MIT License
Classifier: Programming Language :: Python :: 3
Classifier: Programming Language :: Python :: 3.10
Provides-Extra: mongo
Requires-Dist: motor; extra == "mongo"
Provides-Extra: sql
Requires-Dist: sqlalchemy; extra == "sql"
Requires-Dist: alembic; extra == "sql"
Provides-Extra: sqlite
Requires-Dist: sqlalchemy; extra == "sqlite"
Requires-Dist: databases[aiosqlite]>=0.6.1; extra == "sqlite"
Requires-Dist: alembic; extra == "sqlite"
Provides-Extra: testing
Requires-Dist: dbcontroller[mongo,sqlite]; extra == "testing"
